use_event/__init__.py
use_event/core.py
use_event-0.1.0.dist-info/METADATA
use_event-0.1.0.dist-info/WHEEL
use_event-0.1.0.dist-info/RECORD
